MANIFEST.in
README.rst
setup.py
zcbot_shop_parser/__init__.py
zcbot_shop_parser/model.py
zcbot_shop_parser/parser.py
zcbot_shop_parser/utils.py
zcbot_shop_parser.egg-info/PKG-INFO
zcbot_shop_parser.egg-info/SOURCES.txt
zcbot_shop_parser.egg-info/dependency_links.txt
zcbot_shop_parser.egg-info/top_level.txt
zcbot_shop_parser/common/__init__.py
zcbot_shop_parser/common/model.py
zcbot_shop_parser/common/parser.py
zcbot_shop_parser/core/__init__.py
zcbot_shop_parser/core/model.py
zcbot_shop_parser/staples/__init__.py
zcbot_shop_parser/staples/model.py
zcbot_shop_parser/staples/parser.py
zcbot_shop_parser/zcbot/__init__.py
zcbot_shop_parser/zcbot/model.py
zcbot_shop_parser/zcbot/parser.py