Metadata-Version: 2.1
Name: zcbot-shop-parser
Version: 2.0.1
Summary: zcbot shop parser for zsodata
Home-page: http://www.zsodata.com
Author: zsodata
Author-email: team@zso.io
License: BSD License
Platform: all
Requires-Python: >=3.7
